digraph run_cycles { 
        node [shape=box];
        FRAME [label=FRAME];
        OP0 [label="0 LOAD_CONST (False)" color="red"];
        OP2 [label="2 STORE_FAST ('frame_ended')" color="black"];
        OP4 [label="4 LOAD_GLOBAL (range)" color="black"];
        OP6 [label="6 LOAD_FAST ('num_cycles')" color="black"];
        OP8 [label="8 CALL_FUNCTION (1)" color="black"];
        OP10 [label="10 GET_ITER (0)" color="blue"];
        OP12 [label="12 EXTENDED_ARG (1)" color="black"];
        OP14 [label="14 FOR_ITER (381)" color="blue"];
        OP14 -> OP16 [label="Jump (conditional)" color=orange];
        OP14 -> OP778 [label="Jump (conditional)" color=orange];
        OP16 [label="16 STORE_FAST ('cyc')" color="black"];
        OP18 [label="18 LOAD_FAST ('self')" color="black"];
        OP20 [label="20 LOAD_ATTR (line)" color="black"];
        OP22 [label="22 LOAD_CONST (239)" color="red"];
        OP24 [label="24 COMPARE_OP (1)" color="black"];
        OP26 [label="26 POP_JUMP_IF_FALSE (145)" color="red"];
        OP26 -> OP28 [label="Jump (conditional)" color=orange];
        OP26 -> OP290 [label="Jump (conditional)" color=orange];
        OP28 [label="28 LOAD_FAST ('self')" color="black"];
        OP30 [label="30 LOAD_ATTR (ppu_mask)" color="black"];
        OP32 [label="32 LOAD_FAST ('self')" color="black"];
        OP34 [label="34 LOAD_ATTR (RENDERING_ENABLED_MASK)" color="black"];
        OP36 [label="36 BINARY_AND (0)" color="black"];
        OP38 [label="38 LOAD_CONST (0)" color="red"];
        OP40 [label="40 COMPARE_OP (4)" color="black"];
        OP42 [label="42 POP_JUMP_IF_FALSE (145)" color="red"];
        OP42 -> OP44 [label="Jump (conditional)" color=orange];
        OP42 -> OP290 [label="Jump (conditional)" color=orange];
        OP44 [label="44 LOAD_CONST (0)" color="red"];
        OP46 [label="46 LOAD_FAST ('self')" color="black"];
        OP48 [label="48 LOAD_ATTR (pixel)" color="black"];
        OP50 [label="50 DUP_TOP (0)" color="black"];
        OP52 [label="52 ROT_THREE (0)" color="black"];
        OP54 [label="54 COMPARE_OP (0)" color="black"];
        OP56 [label="56 POP_JUMP_IF_FALSE (33)" color="black"];
        OP56 -> OP58 [label="Jump (conditional)" color=orange];
        OP56 -> OP66 [label="Jump (conditional)" color=orange];
        OP58 [label="58 LOAD_CONST (256)" color="red"];
        OP60 [label="60 COMPARE_OP (1)" color="black"];
        OP62 [label="62 POP_JUMP_IF_FALSE (91)" color="black"];
        OP62 -> OP64 [label="Jump (conditional)" color=orange];
        OP62 -> OP182 [label="Jump (conditional)" color=orange];
        OP64 [label="64 JUMP_FORWARD (2)" color="black"];
        OP64 -> OP70 [label="Jump" color=yellow];
        OP66 [label="66 POP_TOP (0)" color="black"];
        OP68 [label="68 JUMP_FORWARD (56)" color="black"];
        OP68 -> OP182 [label="Jump" color=yellow];
        OP70 [label="70 LOAD_FAST ('self')" color="black"];
        OP72 [label="72 LOAD_ATTR (pixel)" color="black"];
        OP74 [label="74 LOAD_CONST (1)" color="red"];
        OP76 [label="76 BINARY_SUBTRACT (0)" color="black"];
        OP78 [label="78 LOAD_CONST (8)" color="red"];
        OP80 [label="80 BINARY_MODULO (0)" color="black"];
        OP82 [label="82 LOAD_CONST (0)" color="red"];
        OP84 [label="84 COMPARE_OP (2)" color="black"];
        OP86 [label="86 POP_JUMP_IF_FALSE (63)" color="black"];
        OP86 -> OP88 [label="Jump (conditional)" color=orange];
        OP86 -> OP126 [label="Jump (conditional)" color=orange];
        OP88 [label="88 LOAD_FAST ('self')" color="black"];
        OP90 [label="90 LOAD_ATTR (pixel)" color="black"];
        OP92 [label="92 LOAD_CONST (1)" color="red"];
        OP94 [label="94 COMPARE_OP (4)" color="black"];
        OP96 [label="96 POP_JUMP_IF_FALSE (63)" color="black"];
        OP96 -> OP98 [label="Jump (conditional)" color=orange];
        OP96 -> OP126 [label="Jump (conditional)" color=orange];
        OP98 [label="98 LOAD_FAST ('self')" color="black"];
        OP100 [label="100 LOAD_METHOD (shift_bkg_latches)" color="black"];
        OP102 [label="102 CALL_METHOD (0)" color="black"];
        OP104 [label="104 POP_TOP (0)" color="black"];
        OP106 [label="106 LOAD_FAST ('self')" color="black"];
        OP108 [label="108 LOAD_METHOD (fill_bkg_latches)" color="black"];
        OP110 [label="110 LOAD_FAST ('self')" color="black"];
        OP112 [label="112 LOAD_ATTR (line)" color="black"];
        OP114 [label="114 LOAD_FAST ('self')" color="black"];
        OP116 [label="116 LOAD_ATTR (col)" color="black"];
        OP118 [label="118 LOAD_CONST (1)" color="red"];
        OP120 [label="120 BINARY_ADD (0)" color="black"];
        OP122 [label="122 CALL_METHOD (2)" color="black"];
        OP124 [label="124 POP_TOP (0)" color="black"];
        OP126 [label="126 LOAD_FAST ('self')" color="black"];
        OP128 [label="128 LOAD_METHOD (_get_bkg_pixel)" color="black"];
        OP130 [label="130 CALL_METHOD (0)" color="black"];
        OP132 [label="132 STORE_FAST ('bkg_pixel')" color="black"];
        OP134 [label="134 LOAD_FAST ('self')" color="black"];
        OP136 [label="136 LOAD_METHOD (_overlay_sprites)" color="black"];
        OP138 [label="138 LOAD_FAST ('bkg_pixel')" color="black"];
        OP140 [label="140 CALL_METHOD (1)" color="black"];
        OP142 [label="142 STORE_FAST ('final_pixel')" color="black"];
        OP144 [label="144 LOAD_FAST ('final_pixel')" color="black"];
        OP146 [label="146 LOAD_FAST ('self')" color="black"];
        OP148 [label="148 LOAD_ATTR (transparent_color)" color="black"];
        OP150 [label="150 COMPARE_OP (3)" color="black"];
        OP152 [label="152 POP_JUMP_IF_FALSE (90)" color="black"];
        OP152 -> OP154 [label="Jump (conditional)" color=orange];
        OP152 -> OP180 [label="Jump (conditional)" color=orange];
        OP154 [label="154 LOAD_FAST ('self')" color="black"];
        OP156 [label="156 LOAD_ATTR (screen)" color="black"];
        OP158 [label="158 LOAD_ATTR (write_at)" color="black"];
        OP160 [label="160 LOAD_FAST ('self')" color="black"];
        OP162 [label="162 LOAD_ATTR (pixel)" color="black"];
        OP164 [label="164 LOAD_CONST (1)" color="red"];
        OP166 [label="166 BINARY_SUBTRACT (0)" color="black"];
        OP168 [label="168 LOAD_FAST ('self')" color="black"];
        OP170 [label="170 LOAD_ATTR (line)" color="black"];
        OP172 [label="172 LOAD_FAST ('final_pixel')" color="black"];
        OP174 [label="174 LOAD_CONST (('x', 'y', 'color'))" color="black"];
        OP176 [label="176 CALL_FUNCTION_KW (3)" color="black"];
        OP178 [label="178 POP_TOP (0)" color="black"];
        OP180 [label="180 JUMP_FORWARD (54)" color="black"];
        OP180 -> OP290 [label="Jump" color=yellow];
        OP182 [label="182 LOAD_FAST ('self')" color="black"];
        OP184 [label="184 LOAD_ATTR (pixel)" color="black"];
        OP186 [label="186 LOAD_CONST (257)" color="red"];
        OP188 [label="188 COMPARE_OP (2)" color="black"];
        OP190 [label="190 POP_JUMP_IF_FALSE (103)" color="black"];
        OP190 -> OP192 [label="Jump (conditional)" color=orange];
        OP190 -> OP206 [label="Jump (conditional)" color=orange];
        OP192 [label="192 LOAD_FAST ('self')" color="black"];
        OP194 [label="194 LOAD_METHOD (_prefetch_active_sprites)" color="black"];
        OP196 [label="196 LOAD_FAST ('self')" color="black"];
        OP198 [label="198 LOAD_ATTR (line)" color="black"];
        OP200 [label="200 CALL_METHOD (1)" color="black"];
        OP202 [label="202 POP_TOP (0)" color="black"];
        OP204 [label="204 JUMP_FORWARD (42)" color="black"];
        OP204 -> OP290 [label="Jump" color=yellow];
        OP206 [label="206 LOAD_CONST (321)" color="red"];
        OP208 [label="208 LOAD_FAST ('self')" color="black"];
        OP210 [label="210 LOAD_ATTR (pixel)" color="black"];
        OP212 [label="212 DUP_TOP (0)" color="black"];
        OP214 [label="214 ROT_THREE (0)" color="black"];
        OP216 [label="216 COMPARE_OP (1)" color="black"];
        OP218 [label="218 POP_JUMP_IF_FALSE (114)" color="black"];
        OP218 -> OP220 [label="Jump (conditional)" color=orange];
        OP218 -> OP228 [label="Jump (conditional)" color=orange];
        OP220 [label="220 LOAD_CONST (336)" color="red"];
        OP222 [label="222 COMPARE_OP (1)" color="black"];
        OP224 [label="224 POP_JUMP_IF_FALSE (144)" color="black"];
        OP224 -> OP226 [label="Jump (conditional)" color=orange];
        OP224 -> OP288 [label="Jump (conditional)" color=orange];
        OP226 [label="226 JUMP_FORWARD (2)" color="black"];
        OP226 -> OP232 [label="Jump" color=yellow];
        OP228 [label="228 POP_TOP (0)" color="black"];
        OP230 [label="230 JUMP_FORWARD (28)" color="black"];
        OP230 -> OP288 [label="Jump" color=yellow];
        OP232 [label="232 LOAD_FAST ('self')" color="black"];
        OP234 [label="234 LOAD_ATTR (pixel)" color="black"];
        OP236 [label="236 LOAD_CONST (8)" color="red"];
        OP238 [label="238 BINARY_MODULO (0)" color="black"];
        OP240 [label="240 LOAD_CONST (1)" color="red"];
        OP242 [label="242 COMPARE_OP (2)" color="black"];
        OP244 [label="244 POP_JUMP_IF_FALSE (143)" color="black"];
        OP244 -> OP246 [label="Jump (conditional)" color=orange];
        OP244 -> OP286 [label="Jump (conditional)" color=orange];
        OP246 [label="246 LOAD_FAST ('self')" color="black"];
        OP248 [label="248 LOAD_METHOD (shift_bkg_latches)" color="black"];
        OP250 [label="250 CALL_METHOD (0)" color="black"];
        OP252 [label="252 POP_TOP (0)" color="black"];
        OP254 [label="254 LOAD_FAST ('self')" color="black"];
        OP256 [label="256 LOAD_METHOD (fill_bkg_latches)" color="black"];
        OP258 [label="258 LOAD_FAST ('self')" color="black"];
        OP260 [label="260 LOAD_ATTR (line)" color="black"];
        OP262 [label="262 LOAD_CONST (1)" color="red"];
        OP264 [label="264 BINARY_ADD (0)" color="black"];
        OP266 [label="266 LOAD_GLOBAL (int)" color="black"];
        OP268 [label="268 LOAD_FAST ('self')" color="black"];
        OP270 [label="270 LOAD_ATTR (pixel)" color="black"];
        OP272 [label="272 LOAD_CONST (321)" color="red"];
        OP274 [label="274 BINARY_SUBTRACT (0)" color="black"];
        OP276 [label="276 LOAD_CONST (8)" color="red"];
        OP278 [label="278 BINARY_TRUE_DIVIDE (0)" color="black"];
        OP280 [label="280 CALL_FUNCTION (1)" color="black"];
        OP282 [label="282 CALL_METHOD (2)" color="black"];
        OP284 [label="284 POP_TOP (0)" color="black"];
        OP286 [label="286 JUMP_FORWARD (1)" color="black"];
        OP286 -> OP290 [label="Jump" color=yellow];
        OP288 [label="288 NOP (0)" color="black"];
        OP290 [label="290 LOAD_FAST ('self')" color="black"];
        OP292 [label="292 LOAD_ATTR (line)" color="black"];
        OP294 [label="294 LOAD_CONST (0)" color="red"];
        OP296 [label="296 COMPARE_OP (2)" color="black"];
        OP298 [label="298 POP_JUMP_IF_FALSE (160)" color="red"];
        OP298 -> OP300 [label="Jump (conditional)" color=orange];
        OP298 -> OP320 [label="Jump (conditional)" color=orange];
        OP300 [label="300 LOAD_FAST ('self')" color="black"];
        OP302 [label="302 LOAD_ATTR (pixel)" color="black"];
        OP304 [label="304 LOAD_CONST (65)" color="red"];
        OP306 [label="306 COMPARE_OP (2)" color="black"];
        OP308 [label="308 POP_JUMP_IF_FALSE (160)" color="red"];
        OP308 -> OP310 [label="Jump (conditional)" color=orange];
        OP308 -> OP320 [label="Jump (conditional)" color=orange];
        OP310 [label="310 LOAD_FAST ('self')" color="black"];
        OP312 [label="312 LOAD_ATTR (oam_addr)" color="black"];
        OP314 [label="314 LOAD_FAST ('self')" color="black"];
        OP316 [label="316 STORE_ATTR (_oam_addr_held)" color="black"];
        OP318 [label="318 JUMP_FORWARD (138)" color="black"];
        OP318 -> OP596 [label="Jump" color=yellow];
        OP320 [label="320 LOAD_FAST ('self')" color="black"];
        OP322 [label="322 LOAD_ATTR (line)" color="black"];
        OP324 [label="324 LOAD_CONST (240)" color="red"];
        OP326 [label="326 COMPARE_OP (2)" color="black"];
        OP328 [label="328 POP_JUMP_IF_FALSE (171)" color="red"];
        OP328 -> OP330 [label="Jump (conditional)" color=orange];
        OP328 -> OP342 [label="Jump (conditional)" color=orange];
        OP330 [label="330 LOAD_FAST ('self')" color="black"];
        OP332 [label="332 LOAD_ATTR (pixel)" color="black"];
        OP334 [label="334 LOAD_CONST (0)" color="red"];
        OP336 [label="336 COMPARE_OP (2)" color="black"];
        OP338 [label="338 POP_JUMP_IF_FALSE (171)" color="black"];
        OP338 -> OP340 [label="Jump (conditional)" color=orange];
        OP338 -> OP342 [label="Jump (conditional)" color=orange];
        OP340 [label="340 JUMP_FORWARD (127)" color="black"];
        OP340 -> OP596 [label="Jump" color=yellow];
        OP342 [label="342 LOAD_FAST ('self')" color="black"];
        OP344 [label="344 LOAD_ATTR (line)" color="black"];
        OP346 [label="346 LOAD_CONST (241)" color="red"];
        OP348 [label="348 COMPARE_OP (2)" color="black"];
        OP350 [label="350 POP_JUMP_IF_FALSE (197)" color="red"];
        OP350 -> OP352 [label="Jump (conditional)" color=orange];
        OP350 -> OP394 [label="Jump (conditional)" color=orange];
        OP352 [label="352 LOAD_FAST ('self')" color="black"];
        OP354 [label="354 LOAD_ATTR (pixel)" color="black"];
        OP356 [label="356 LOAD_CONST (1)" color="red"];
        OP358 [label="358 COMPARE_OP (2)" color="black"];
        OP360 [label="360 POP_JUMP_IF_FALSE (197)" color="black"];
        OP360 -> OP362 [label="Jump (conditional)" color=orange];
        OP360 -> OP394 [label="Jump (conditional)" color=orange];
        OP362 [label="362 LOAD_CONST (True)" color="red"];
        OP364 [label="364 LOAD_FAST ('self')" color="black"];
        OP366 [label="366 STORE_ATTR (in_vblank)" color="black"];
        OP368 [label="368 LOAD_FAST ('self')" color="black"];
        OP370 [label="370 LOAD_ATTR (ppu_ctrl)" color="black"];
        OP372 [label="372 LOAD_FAST ('self')" color="black"];
        OP374 [label="374 LOAD_ATTR (VBLANK_MASK)" color="black"];
        OP376 [label="376 BINARY_AND (0)" color="black"];
        OP378 [label="378 LOAD_CONST (0)" color="red"];
        OP380 [label="380 COMPARE_OP (4)" color="black"];
        OP382 [label="382 POP_JUMP_IF_FALSE (196)" color="black"];
        OP382 -> OP384 [label="Jump (conditional)" color=orange];
        OP382 -> OP392 [label="Jump (conditional)" color=orange];
        OP384 [label="384 LOAD_FAST ('self')" color="black"];
        OP386 [label="386 LOAD_METHOD (_trigger_nmi)" color="black"];
        OP388 [label="388 CALL_METHOD (0)" color="black"];
        OP390 [label="390 POP_TOP (0)" color="black"];
        OP392 [label="392 JUMP_FORWARD (101)" color="black"];
        OP392 -> OP596 [label="Jump" color=yellow];
        OP394 [label="394 LOAD_CONST (241)" color="red"];
        OP396 [label="396 LOAD_FAST ('self')" color="black"];
        OP398 [label="398 LOAD_ATTR (line)" color="black"];
        OP400 [label="400 DUP_TOP (0)" color="black"];
        OP402 [label="402 ROT_THREE (0)" color="black"];
        OP404 [label="404 COMPARE_OP (1)" color="black"];
        OP406 [label="406 POP_JUMP_IF_FALSE (208)" color="red"];
        OP406 -> OP408 [label="Jump (conditional)" color=orange];
        OP406 -> OP416 [label="Jump (conditional)" color=orange];
        OP408 [label="408 LOAD_CONST (260)" color="red"];
        OP410 [label="410 COMPARE_OP (1)" color="black"];
        OP412 [label="412 POP_JUMP_IF_FALSE (211)" color="black"];
        OP412 -> OP414 [label="Jump (conditional)" color=orange];
        OP412 -> OP422 [label="Jump (conditional)" color=orange];
        OP414 [label="414 JUMP_FORWARD (2)" color="black"];
        OP414 -> OP420 [label="Jump" color=yellow];
        OP416 [label="416 POP_TOP (0)" color="black"];
        OP418 [label="418 JUMP_FORWARD (1)" color="black"];
        OP418 -> OP422 [label="Jump" color=yellow];
        OP420 [label="420 JUMP_FORWARD (87)" color="black"];
        OP420 -> OP596 [label="Jump" color=yellow];
        OP422 [label="422 LOAD_FAST ('self')" color="black"];
        OP424 [label="424 LOAD_ATTR (line)" color="black"];
        OP426 [label="426 LOAD_CONST (261)" color="red"];
        OP428 [label="428 COMPARE_OP (2)" color="black"];
        OP430 [label="430 EXTENDED_ARG (1)" color="black"];
        OP432 [label="432 POP_JUMP_IF_FALSE (298)" color="red"];
        OP432 -> OP434 [label="Jump (conditional)" color=orange];
        OP432 -> OP596 [label="Jump (conditional)" color=orange];
        OP434 [label="434 LOAD_FAST ('self')" color="black"];
        OP436 [label="436 LOAD_ATTR (pixel)" color="black"];
        OP438 [label="438 LOAD_CONST (1)" color="red"];
        OP440 [label="440 COMPARE_OP (2)" color="black"];
        OP442 [label="442 POP_JUMP_IF_FALSE (232)" color="black"];
        OP442 -> OP444 [label="Jump (conditional)" color=orange];
        OP442 -> OP464 [label="Jump (conditional)" color=orange];
        OP444 [label="444 LOAD_CONST (False)" color="red"];
        OP446 [label="446 LOAD_FAST ('self')" color="black"];
        OP448 [label="448 STORE_ATTR (in_vblank)" color="black"];
        OP450 [label="450 LOAD_CONST (False)" color="red"];
        OP452 [label="452 LOAD_FAST ('self')" color="black"];
        OP454 [label="454 STORE_ATTR (sprite_zero_hit)" color="black"];
        OP456 [label="456 LOAD_CONST (False)" color="red"];
        OP458 [label="458 LOAD_FAST ('self')" color="black"];
        OP460 [label="460 STORE_ATTR (sprite_overflow)" color="black"];
        OP462 [label="462 JUMP_FORWARD (66)" color="black"];
        OP462 -> OP596 [label="Jump" color=yellow];
        OP464 [label="464 LOAD_FAST ('self')" color="black"];
        OP466 [label="466 LOAD_ATTR (pixel)" color="black"];
        OP468 [label="468 LOAD_CONST (257)" color="red"];
        OP470 [label="470 COMPARE_OP (2)" color="black"];
        OP472 [label="472 POP_JUMP_IF_FALSE (241)" color="black"];
        OP472 -> OP474 [label="Jump (conditional)" color=orange];
        OP472 -> OP482 [label="Jump (conditional)" color=orange];
        OP474 [label="474 BUILD_LIST (0)" color="black"];
        OP476 [label="476 LOAD_FAST ('self')" color="black"];
        OP478 [label="478 STORE_ATTR (_active_sprites)" color="black"];
        OP480 [label="480 JUMP_FORWARD (57)" color="black"];
        OP480 -> OP596 [label="Jump" color=yellow];
        OP482 [label="482 LOAD_CONST (321)" color="red"];
        OP484 [label="484 LOAD_FAST ('self')" color="black"];
        OP486 [label="486 LOAD_ATTR (pixel)" color="black"];
        OP488 [label="488 DUP_TOP (0)" color="black"];
        OP490 [label="490 ROT_THREE (0)" color="black"];
        OP492 [label="492 COMPARE_OP (1)" color="black"];
        OP494 [label="494 POP_JUMP_IF_FALSE (253)" color="black"];
        OP494 -> OP496 [label="Jump (conditional)" color=orange];
        OP494 -> OP506 [label="Jump (conditional)" color=orange];
        OP496 [label="496 LOAD_CONST (336)" color="red"];
        OP498 [label="498 COMPARE_OP (1)" color="black"];
        OP500 [label="500 EXTENDED_ARG (1)" color="black"];
        OP502 [label="502 POP_JUMP_IF_FALSE (282)" color="black"];
        OP502 -> OP504 [label="Jump (conditional)" color=orange];
        OP502 -> OP564 [label="Jump (conditional)" color=orange];
        OP504 [label="504 JUMP_FORWARD (2)" color="black"];
        OP504 -> OP510 [label="Jump" color=yellow];
        OP506 [label="506 POP_TOP (0)" color="black"];
        OP508 [label="508 JUMP_FORWARD (27)" color="black"];
        OP508 -> OP564 [label="Jump" color=yellow];
        OP510 [label="510 LOAD_FAST ('self')" color="black"];
        OP512 [label="512 LOAD_ATTR (pixel)" color="black"];
        OP514 [label="514 LOAD_CONST (8)" color="red"];
        OP516 [label="516 BINARY_MODULO (0)" color="black"];
        OP518 [label="518 LOAD_CONST (1)" color="red"];
        OP520 [label="520 COMPARE_OP (2)" color="black"];
        OP522 [label="522 EXTENDED_ARG (1)" color="black"];
        OP524 [label="524 POP_JUMP_IF_FALSE (281)" color="black"];
        OP524 -> OP526 [label="Jump (conditional)" color=orange];
        OP524 -> OP562 [label="Jump (conditional)" color=orange];
        OP526 [label="526 LOAD_FAST ('self')" color="black"];
        OP528 [label="528 LOAD_METHOD (shift_bkg_latches)" color="black"];
        OP530 [label="530 CALL_METHOD (0)" color="black"];
        OP532 [label="532 POP_TOP (0)" color="black"];
        OP534 [label="534 LOAD_FAST ('self')" color="black"];
        OP536 [label="536 LOAD_ATTR (fill_bkg_latches)" color="black"];
        OP538 [label="538 LOAD_CONST (0)" color="red"];
        OP540 [label="540 LOAD_GLOBAL (int)" color="black"];
        OP542 [label="542 LOAD_FAST ('self')" color="black"];
        OP544 [label="544 LOAD_ATTR (pixel)" color="black"];
        OP546 [label="546 LOAD_CONST (321)" color="red"];
        OP548 [label="548 BINARY_SUBTRACT (0)" color="black"];
        OP550 [label="550 LOAD_CONST (8)" color="red"];
        OP552 [label="552 BINARY_TRUE_DIVIDE (0)" color="black"];
        OP554 [label="554 CALL_FUNCTION (1)" color="black"];
        OP556 [label="556 LOAD_CONST (('line', 'col'))" color="black"];
        OP558 [label="558 CALL_FUNCTION_KW (2)" color="black"];
        OP560 [label="560 POP_TOP (0)" color="black"];
        OP562 [label="562 JUMP_FORWARD (16)" color="black"];
        OP562 -> OP596 [label="Jump" color=yellow];
        OP564 [label="564 LOAD_FAST ('self')" color="black"];
        OP566 [label="566 LOAD_ATTR (pixel)" color="black"];
        OP568 [label="568 LOAD_FAST ('self')" color="black"];
        OP570 [label="570 LOAD_ATTR (PIXELS_PER_LINE)" color="black"];
        OP572 [label="572 LOAD_CONST (1)" color="red"];
        OP574 [label="574 BINARY_SUBTRACT (0)" color="black"];
        OP576 [label="576 LOAD_FAST ('self')" color="black"];
        OP578 [label="578 LOAD_ATTR (frames_since_reset)" color="black"];
        OP580 [label="580 LOAD_CONST (2)" color="red"];
        OP582 [label="582 BINARY_MODULO (0)" color="black"];
        OP584 [label="584 BINARY_SUBTRACT (0)" color="black"];
        OP586 [label="586 COMPARE_OP (2)" color="black"];
        OP588 [label="588 EXTENDED_ARG (1)" color="black"];
        OP590 [label="590 POP_JUMP_IF_FALSE (298)" color="black"];
        OP590 -> OP592 [label="Jump (conditional)" color=orange];
        OP590 -> OP596 [label="Jump (conditional)" color=orange];
        OP592 [label="592 LOAD_CONST (True)" color="red"];
        OP594 [label="594 STORE_FAST ('frame_ended')" color="black"];
        OP596 [label="596 LOAD_FAST ('self')" color="black"];
        OP598 [label="598 DUP_TOP (0)" color="black"];
        OP600 [label="600 LOAD_ATTR (cycles_since_reset)" color="black"];
        OP602 [label="602 LOAD_CONST (1)" color="red"];
        OP604 [label="604 INPLACE_ADD (0)" color="black"];
        OP606 [label="606 ROT_TWO (0)" color="black"];
        OP608 [label="608 STORE_ATTR (cycles_since_reset)" color="black"];
        OP610 [label="610 LOAD_FAST ('self')" color="black"];
        OP612 [label="612 DUP_TOP (0)" color="black"];
        OP614 [label="614 LOAD_ATTR (cycles_since_frame)" color="black"];
        OP616 [label="616 LOAD_CONST (1)" color="red"];
        OP618 [label="618 INPLACE_ADD (0)" color="black"];
        OP620 [label="620 ROT_TWO (0)" color="black"];
        OP622 [label="622 STORE_ATTR (cycles_since_frame)" color="black"];
        OP624 [label="624 LOAD_FAST ('self')" color="black"];
        OP626 [label="626 DUP_TOP (0)" color="black"];
        OP628 [label="628 LOAD_ATTR (pixel)" color="black"];
        OP630 [label="630 LOAD_CONST (1)" color="red"];
        OP632 [label="632 INPLACE_ADD (0)" color="black"];
        OP634 [label="634 ROT_TWO (0)" color="black"];
        OP636 [label="636 STORE_ATTR (pixel)" color="black"];
        OP638 [label="638 LOAD_FAST ('self')" color="black"];
        OP640 [label="640 LOAD_ATTR (pixel)" color="black"];
        OP642 [label="642 LOAD_CONST (1)" color="red"];
        OP644 [label="644 COMPARE_OP (4)" color="black"];
        OP646 [label="646 EXTENDED_ARG (1)" color="black"];
        OP648 [label="648 POP_JUMP_IF_FALSE (340)" color="red"];
        OP648 -> OP650 [label="Jump (conditional)" color=orange];
        OP648 -> OP680 [label="Jump (conditional)" color=orange];
        OP650 [label="650 LOAD_FAST ('self')" color="black"];
        OP652 [label="652 LOAD_ATTR (pixel)" color="black"];
        OP654 [label="654 LOAD_CONST (8)" color="red"];
        OP656 [label="656 BINARY_MODULO (0)" color="black"];
        OP658 [label="658 LOAD_CONST (1)" color="red"];
        OP660 [label="660 COMPARE_OP (2)" color="black"];
        OP662 [label="662 EXTENDED_ARG (1)" color="black"];
        OP664 [label="664 POP_JUMP_IF_FALSE (340)" color="red"];
        OP664 -> OP666 [label="Jump (conditional)" color=orange];
        OP664 -> OP680 [label="Jump (conditional)" color=orange];
        OP666 [label="666 LOAD_FAST ('self')" color="black"];
        OP668 [label="668 DUP_TOP (0)" color="black"];
        OP670 [label="670 LOAD_ATTR (col)" color="black"];
        OP672 [label="672 LOAD_CONST (1)" color="red"];
        OP674 [label="674 INPLACE_ADD (0)" color="black"];
        OP676 [label="676 ROT_TWO (0)" color="black"];
        OP678 [label="678 STORE_ATTR (col)" color="black"];
        OP680 [label="680 LOAD_FAST ('self')" color="black"];
        OP682 [label="682 LOAD_ATTR (pixel)" color="black"];
        OP684 [label="684 LOAD_FAST ('self')" color="black"];
        OP686 [label="686 LOAD_ATTR (PIXELS_PER_LINE)" color="black"];
        OP688 [label="688 COMPARE_OP (5)" color="black"];
        OP690 [label="690 EXTENDED_ARG (1)" color="black"];
        OP692 [label="692 POP_JUMP_IF_FALSE (381)" color="red"];
        OP692 -> OP694 [label="Jump (conditional)" color=orange];
        OP692 -> OP762 [label="Jump (conditional)" color=orange];
        OP694 [label="694 LOAD_FAST ('self')" color="black"];
        OP696 [label="696 DUP_TOP (0)" color="black"];
        OP698 [label="698 LOAD_ATTR (line)" color="black"];
        OP700 [label="700 LOAD_CONST (1)" color="red"];
        OP702 [label="702 INPLACE_ADD (0)" color="black"];
        OP704 [label="704 ROT_TWO (0)" color="black"];
        OP706 [label="706 STORE_ATTR (line)" color="black"];
        OP708 [label="708 LOAD_CONST (0)" color="red"];
        OP710 [label="710 LOAD_FAST ('self')" color="black"];
        OP712 [label="712 STORE_ATTR (pixel)" color="black"];
        OP714 [label="714 LOAD_CONST (0)" color="red"];
        OP716 [label="716 LOAD_FAST ('self')" color="black"];
        OP718 [label="718 STORE_ATTR (col)" color="black"];
        OP720 [label="720 LOAD_FAST ('self')" color="black"];
        OP722 [label="722 LOAD_ATTR (line)" color="black"];
        OP724 [label="724 LOAD_CONST (0)" color="red"];
        OP726 [label="726 COMPARE_OP (4)" color="black"];
        OP728 [label="728 EXTENDED_ARG (1)" color="black"];
        OP730 [label="730 POP_JUMP_IF_FALSE (381)" color="black"];
        OP730 -> OP732 [label="Jump (conditional)" color=orange];
        OP730 -> OP762 [label="Jump (conditional)" color=orange];
        OP732 [label="732 LOAD_FAST ('self')" color="black"];
        OP734 [label="734 LOAD_ATTR (line)" color="black"];
        OP736 [label="736 LOAD_CONST (8)" color="red"];
        OP738 [label="738 BINARY_MODULO (0)" color="black"];
        OP740 [label="740 LOAD_CONST (0)" color="red"];
        OP742 [label="742 COMPARE_OP (2)" color="black"];
        OP744 [label="744 EXTENDED_ARG (1)" color="black"];
        OP746 [label="746 POP_JUMP_IF_FALSE (381)" color="black"];
        OP746 -> OP748 [label="Jump (conditional)" color=orange];
        OP746 -> OP762 [label="Jump (conditional)" color=orange];
        OP748 [label="748 LOAD_FAST ('self')" color="black"];
        OP750 [label="750 DUP_TOP (0)" color="black"];
        OP752 [label="752 LOAD_ATTR (row)" color="black"];
        OP754 [label="754 LOAD_CONST (1)" color="red"];
        OP756 [label="756 INPLACE_ADD (0)" color="black"];
        OP758 [label="758 ROT_TWO (0)" color="black"];
        OP760 [label="760 STORE_ATTR (row)" color="black"];
        OP762 [label="762 LOAD_FAST ('frame_ended')" color="black"];
        OP764 [label="764 EXTENDED_ARG (1)" color="black"];
        OP766 [label="766 POP_JUMP_IF_FALSE (388)" color="red"];
        OP766 -> OP768 [label="Jump (conditional)" color=orange];
        OP766 -> OP776 [label="Jump (conditional)" color=orange];
        OP768 [label="768 LOAD_FAST ('self')" color="black"];
        OP770 [label="770 LOAD_METHOD (_new_frame)" color="black"];
        OP772 [label="772 CALL_METHOD (0)" color="black"];
        OP774 [label="774 POP_TOP (0)" color="black"];
        OP776 [label="776 JUMP_ABSOLUTE (6)" color="black"];
        OP776 -> OP12 [label="Jump" color=yellow];
        OP778 [label="778 LOAD_FAST ('frame_ended')" color="black"];
        OP780 [label="780 RETURN_VALUE (0)" color="black"];
        OP0 -> OP2 [label="Const (bool) -0" color=black];
        OP4 -> OP8 [label="Builtin (type) -1" color=black];
        OP6 -> OP8 [label="Local (int) -0" color=black];
        OP8 -> OP10 [label="Local (range) U0" color=red];
        OP10 -> OP14 [label="Intermediate (unboxed range iterator) UN0" color=purple];
        OP14 -> OP16 [label="Intermediate (int) B0" color=green];
        OP18 -> OP20 [label="Local (NESPPU) -0" color=black];
        OP20 -> OP24 [label="Intermediate (int) -1" color=black];
        OP22 -> OP24 [label="Const (int) -0" color=black];
        OP24 -> OP26 [label="Intermediate (bool) -0" color=black];
        OP28 -> OP30 [label="Local (NESPPU) -0" color=black];
        OP32 -> OP34 [label="Local (NESPPU) -0" color=black];
        OP30 -> OP36 [label="Intermediate (int) -1" color=black];
        OP34 -> OP36 [label="Intermediate (int) -0" color=black];
        OP36 -> OP40 [label="Intermediate (big int) -1" color=black];
        OP38 -> OP40 [label="Const (int) -0" color=black];
        OP40 -> OP42 [label="Intermediate (bool) -0" color=black];
        OP46 -> OP48 [label="Local (NESPPU) -0" color=black];
        OP48 -> OP50 [label="Intermediate (Any) -0" color=black];
        OP44 -> OP52 [label="Const (int) -2" color=black];
        OP50 -> OP52 [label="Intermediate (Any) -1" color=black];
        OP50 -> OP52 [label="Intermediate (Any) -0" color=black];
        OP52 -> OP54 [label="Intermediate (int) -1" color=black];
        OP52 -> OP54 [label="Intermediate (Any) -0" color=black];
        OP54 -> OP56 [label="Intermediate (Any) -0" color=black];
        OP52 -> OP60 [label="Intermediate (Any) -1" color=black];
        OP58 -> OP60 [label="Const (int) -0" color=black];
        OP60 -> OP62 [label="Intermediate (Any) -0" color=black];
        OP52 -> OP66 [label="Intermediate (Any) -0" color=black];
        OP70 -> OP72 [label="Local (NESPPU) -0" color=black];
        OP72 -> OP76 [label="Intermediate (Any) -1" color=black];
        OP74 -> OP76 [label="Const (int) -0" color=black];
        OP76 -> OP80 [label="Intermediate (Any) -1" color=black];
        OP78 -> OP80 [label="Const (int) -0" color=black];
        OP80 -> OP84 [label="Intermediate (Any) -1" color=black];
        OP82 -> OP84 [label="Const (int) -0" color=black];
        OP84 -> OP86 [label="Intermediate (Any) -0" color=black];
        OP88 -> OP90 [label="Local (NESPPU) -0" color=black];
        OP90 -> OP94 [label="Intermediate (Any) -1" color=black];
        OP92 -> OP94 [label="Const (int) -0" color=black];
        OP94 -> OP96 [label="Intermediate (Any) -0" color=black];
        OP98 -> OP100 [label="Local (NESPPU) -0" color=black];
        OP100 -> OP102 [label="Intermediate (NESPPU) -1" color=black];
        OP100 -> OP102 [label="Method (method) -0" color=black];
        OP102 -> OP104 [label="Intermediate (Any) -0" color=black];
        OP106 -> OP108 [label="Local (NESPPU) -0" color=black];
        OP110 -> OP112 [label="Local (NESPPU) -0" color=black];
        OP114 -> OP116 [label="Local (NESPPU) -0" color=black];
        OP116 -> OP120 [label="Intermediate (Any) -1" color=black];
        OP118 -> OP120 [label="Const (int) -0" color=black];
        OP108 -> OP122 [label="Intermediate (NESPPU) -3" color=black];
        OP108 -> OP122 [label="Method (method) -2" color=black];
        OP112 -> OP122 [label="Intermediate (Any) -1" color=black];
        OP120 -> OP122 [label="Intermediate (Any) -0" color=black];
        OP122 -> OP124 [label="Intermediate (Any) -0" color=black];
        OP126 -> OP128 [label="Local (NESPPU) -0" color=black];
        OP128 -> OP130 [label="Intermediate (NESPPU) -1" color=black];
        OP128 -> OP130 [label="Method (method) -0" color=black];
        OP130 -> OP132 [label="Intermediate (Any) -0" color=black];
        OP134 -> OP136 [label="Local (NESPPU) -0" color=black];
        OP136 -> OP140 [label="Intermediate (NESPPU) -2" color=black];
        OP136 -> OP140 [label="Method (method) -1" color=black];
        OP138 -> OP140 [label="Local (Any) -0" color=black];
        OP140 -> OP142 [label="Intermediate (Any) -0" color=black];
        OP146 -> OP148 [label="Local (NESPPU) -0" color=black];
        OP144 -> OP150 [label="Local (Any) -1" color=black];
        OP148 -> OP150 [label="Intermediate (Any) -0" color=black];
        OP150 -> OP152 [label="Intermediate (Any) -0" color=black];
        OP154 -> OP156 [label="Local (NESPPU) -0" color=black];
        OP156 -> OP158 [label="Intermediate (Any) -0" color=black];
        OP160 -> OP162 [label="Local (NESPPU) -0" color=black];
        OP162 -> OP166 [label="Intermediate (Any) -1" color=black];
        OP164 -> OP166 [label="Const (int) -0" color=black];
        OP168 -> OP170 [label="Local (NESPPU) -0" color=black];
        OP158 -> OP176 [label="Intermediate (Any) -4" color=black];
        OP166 -> OP176 [label="Intermediate (Any) -3" color=black];
        OP170 -> OP176 [label="Intermediate (Any) -2" color=black];
        OP172 -> OP176 [label="Local (Any) -1" color=black];
        OP174 -> OP176 [label="Const (tuple) -0" color=black];
        OP176 -> OP178 [label="Intermediate (Any) -0" color=black];
        OP182 -> OP184 [label="Local (NESPPU) -0" color=black];
        OP184 -> OP188 [label="Intermediate (Any) -1" color=black];
        OP186 -> OP188 [label="Const (int) -0" color=black];
        OP188 -> OP190 [label="Intermediate (Any) -0" color=black];
        OP192 -> OP194 [label="Local (NESPPU) -0" color=black];
        OP196 -> OP198 [label="Local (NESPPU) -0" color=black];
        OP194 -> OP200 [label="Intermediate (NESPPU) -2" color=black];
        OP194 -> OP200 [label="Method (method) -1" color=black];
        OP198 -> OP200 [label="Intermediate (Any) -0" color=black];
        OP200 -> OP202 [label="Intermediate (Any) -0" color=black];
        OP208 -> OP210 [label="Local (NESPPU) -0" color=black];
        OP210 -> OP212 [label="Intermediate (Any) -0" color=black];
        OP206 -> OP214 [label="Const (int) -2" color=black];
        OP212 -> OP214 [label="Intermediate (Any) -1" color=black];
        OP212 -> OP214 [label="Intermediate (Any) -0" color=black];
        OP214 -> OP216 [label="Intermediate (int) -1" color=black];
        OP214 -> OP216 [label="Intermediate (Any) -0" color=black];
        OP216 -> OP218 [label="Intermediate (Any) -0" color=black];
        OP214 -> OP222 [label="Intermediate (Any) -1" color=black];
        OP220 -> OP222 [label="Const (int) -0" color=black];
        OP222 -> OP224 [label="Intermediate (Any) -0" color=black];
        OP214 -> OP228 [label="Intermediate (Any) -0" color=black];
        OP232 -> OP234 [label="Local (NESPPU) -0" color=black];
        OP234 -> OP238 [label="Intermediate (Any) -1" color=black];
        OP236 -> OP238 [label="Const (int) -0" color=black];
        OP238 -> OP242 [label="Intermediate (Any) -1" color=black];
        OP240 -> OP242 [label="Const (int) -0" color=black];
        OP242 -> OP244 [label="Intermediate (Any) -0" color=black];
        OP246 -> OP248 [label="Local (NESPPU) -0" color=black];
        OP248 -> OP250 [label="Intermediate (NESPPU) -1" color=black];
        OP248 -> OP250 [label="Method (method) -0" color=black];
        OP250 -> OP252 [label="Intermediate (Any) -0" color=black];
        OP254 -> OP256 [label="Local (NESPPU) -0" color=black];
        OP258 -> OP260 [label="Local (NESPPU) -0" color=black];
        OP260 -> OP264 [label="Intermediate (Any) -1" color=black];
        OP262 -> OP264 [label="Const (int) -0" color=black];
        OP268 -> OP270 [label="Local (NESPPU) -0" color=black];
        OP270 -> OP274 [label="Intermediate (Any) -1" color=black];
        OP272 -> OP274 [label="Const (int) -0" color=black];
        OP274 -> OP278 [label="Intermediate (Any) -1" color=black];
        OP276 -> OP278 [label="Const (int) -0" color=black];
        OP266 -> OP280 [label="Builtin (type) -1" color=black];
        OP278 -> OP280 [label="Intermediate (Any) -0" color=black];
        OP256 -> OP282 [label="Intermediate (NESPPU) -3" color=black];
        OP256 -> OP282 [label="Method (method) -2" color=black];
        OP264 -> OP282 [label="Intermediate (Any) -1" color=black];
        OP280 -> OP282 [label="Local (big int) -0" color=black];
        OP282 -> OP284 [label="Intermediate (Any) -0" color=black];
        OP290 -> OP292 [label="Local (NESPPU) -0" color=black];
        OP292 -> OP296 [label="Intermediate (int) -1" color=black];
        OP294 -> OP296 [label="Const (int) -0" color=black];
        OP296 -> OP298 [label="Intermediate (bool) -0" color=black];
        OP300 -> OP302 [label="Local (NESPPU) -0" color=black];
        OP302 -> OP306 [label="Intermediate (int) -1" color=black];
        OP304 -> OP306 [label="Const (int) -0" color=black];
        OP306 -> OP308 [label="Intermediate (bool) -0" color=black];
        OP310 -> OP312 [label="Local (NESPPU) -0" color=black];
        OP312 -> OP316 [label="Intermediate (Any) -1" color=black];
        OP314 -> OP316 [label="Local (NESPPU) -0" color=black];
        OP320 -> OP322 [label="Local (NESPPU) -0" color=black];
        OP322 -> OP326 [label="Intermediate (int) -1" color=black];
        OP324 -> OP326 [label="Const (int) -0" color=black];
        OP326 -> OP328 [label="Intermediate (bool) -0" color=black];
        OP330 -> OP332 [label="Local (NESPPU) -0" color=black];
        OP332 -> OP336 [label="Intermediate (Any) -1" color=black];
        OP334 -> OP336 [label="Const (int) -0" color=black];
        OP336 -> OP338 [label="Intermediate (Any) -0" color=black];
        OP342 -> OP344 [label="Local (NESPPU) -0" color=black];
        OP344 -> OP348 [label="Intermediate (int) -1" color=black];
        OP346 -> OP348 [label="Const (int) -0" color=black];
        OP348 -> OP350 [label="Intermediate (bool) -0" color=black];
        OP352 -> OP354 [label="Local (NESPPU) -0" color=black];
        OP354 -> OP358 [label="Intermediate (Any) -1" color=black];
        OP356 -> OP358 [label="Const (int) -0" color=black];
        OP358 -> OP360 [label="Intermediate (Any) -0" color=black];
        OP362 -> OP366 [label="Const (bool) -1" color=black];
        OP364 -> OP366 [label="Local (NESPPU) -0" color=black];
        OP368 -> OP370 [label="Local (NESPPU) -0" color=black];
        OP372 -> OP374 [label="Local (NESPPU) -0" color=black];
        OP370 -> OP376 [label="Intermediate (Any) -1" color=black];
        OP374 -> OP376 [label="Intermediate (Any) -0" color=black];
        OP376 -> OP380 [label="Intermediate (Any) -1" color=black];
        OP378 -> OP380 [label="Const (int) -0" color=black];
        OP380 -> OP382 [label="Intermediate (Any) -0" color=black];
        OP384 -> OP386 [label="Local (NESPPU) -0" color=black];
        OP386 -> OP388 [label="Intermediate (NESPPU) -1" color=black];
        OP386 -> OP388 [label="Method (method) -0" color=black];
        OP388 -> OP390 [label="Intermediate (Any) -0" color=black];
        OP396 -> OP398 [label="Local (NESPPU) -0" color=black];
        OP398 -> OP400 [label="Intermediate (Any) -0" color=black];
        OP394 -> OP402 [label="Const (int) -2" color=black];
        OP400 -> OP402 [label="Intermediate (Any) -1" color=black];
        OP400 -> OP402 [label="Intermediate (Any) -0" color=black];
        OP402 -> OP404 [label="Intermediate (int) -1" color=black];
        OP402 -> OP404 [label="Intermediate (int) -0" color=black];
        OP404 -> OP406 [label="Intermediate (bool) -0" color=black];
        OP402 -> OP410 [label="Intermediate (Any) -1" color=black];
        OP408 -> OP410 [label="Const (int) -0" color=black];
        OP410 -> OP412 [label="Intermediate (Any) -0" color=black];
        OP402 -> OP416 [label="Intermediate (Any) -0" color=black];
        OP422 -> OP424 [label="Local (NESPPU) -0" color=black];
        OP424 -> OP428 [label="Intermediate (int) -1" color=black];
        OP426 -> OP428 [label="Const (int) -0" color=black];
        OP428 -> OP432 [label="Intermediate (bool) -0" color=black];
        OP434 -> OP436 [label="Local (NESPPU) -0" color=black];
        OP436 -> OP440 [label="Intermediate (Any) -1" color=black];
        OP438 -> OP440 [label="Const (int) -0" color=black];
        OP440 -> OP442 [label="Intermediate (Any) -0" color=black];
        OP444 -> OP448 [label="Const (bool) -1" color=black];
        OP446 -> OP448 [label="Local (NESPPU) -0" color=black];
        OP450 -> OP454 [label="Const (bool) -1" color=black];
        OP452 -> OP454 [label="Local (NESPPU) -0" color=black];
        OP456 -> OP460 [label="Const (bool) -1" color=black];
        OP458 -> OP460 [label="Local (NESPPU) -0" color=black];
        OP464 -> OP466 [label="Local (NESPPU) -0" color=black];
        OP466 -> OP470 [label="Intermediate (Any) -1" color=black];
        OP468 -> OP470 [label="Const (int) -0" color=black];
        OP470 -> OP472 [label="Intermediate (Any) -0" color=black];
        OP474 -> OP478 [label="Intermediate (list) -1" color=black];
        OP476 -> OP478 [label="Local (NESPPU) -0" color=black];
        OP484 -> OP486 [label="Local (NESPPU) -0" color=black];
        OP486 -> OP488 [label="Intermediate (Any) -0" color=black];
        OP482 -> OP490 [label="Const (int) -2" color=black];
        OP488 -> OP490 [label="Intermediate (Any) -1" color=black];
        OP488 -> OP490 [label="Intermediate (Any) -0" color=black];
        OP490 -> OP492 [label="Intermediate (int) -1" color=black];
        OP490 -> OP492 [label="Intermediate (Any) -0" color=black];
        OP492 -> OP494 [label="Intermediate (Any) -0" color=black];
        OP490 -> OP498 [label="Intermediate (Any) -1" color=black];
        OP496 -> OP498 [label="Const (int) -0" color=black];
        OP498 -> OP502 [label="Intermediate (Any) -0" color=black];
        OP490 -> OP506 [label="Intermediate (Any) -0" color=black];
        OP510 -> OP512 [label="Local (NESPPU) -0" color=black];
        OP512 -> OP516 [label="Intermediate (Any) -1" color=black];
        OP514 -> OP516 [label="Const (int) -0" color=black];
        OP516 -> OP520 [label="Intermediate (Any) -1" color=black];
        OP518 -> OP520 [label="Const (int) -0" color=black];
        OP520 -> OP524 [label="Intermediate (Any) -0" color=black];
        OP526 -> OP528 [label="Local (NESPPU) -0" color=black];
        OP528 -> OP530 [label="Intermediate (NESPPU) -1" color=black];
        OP528 -> OP530 [label="Method (method) -0" color=black];
        OP530 -> OP532 [label="Intermediate (Any) -0" color=black];
        OP534 -> OP536 [label="Local (NESPPU) -0" color=black];
        OP542 -> OP544 [label="Local (NESPPU) -0" color=black];
        OP544 -> OP548 [label="Intermediate (Any) -1" color=black];
        OP546 -> OP548 [label="Const (int) -0" color=black];
        OP548 -> OP552 [label="Intermediate (Any) -1" color=black];
        OP550 -> OP552 [label="Const (int) -0" color=black];
        OP540 -> OP554 [label="Builtin (type) -1" color=black];
        OP552 -> OP554 [label="Intermediate (Any) -0" color=black];
        OP536 -> OP558 [label="Intermediate (Any) -3" color=black];
        OP538 -> OP558 [label="Const (int) -2" color=black];
        OP554 -> OP558 [label="Local (big int) -1" color=black];
        OP556 -> OP558 [label="Const (tuple) -0" color=black];
        OP558 -> OP560 [label="Intermediate (Any) -0" color=black];
        OP564 -> OP566 [label="Local (NESPPU) -0" color=black];
        OP568 -> OP570 [label="Local (NESPPU) -0" color=black];
        OP570 -> OP574 [label="Intermediate (Any) -1" color=black];
        OP572 -> OP574 [label="Const (int) -0" color=black];
        OP576 -> OP578 [label="Local (NESPPU) -0" color=black];
        OP578 -> OP582 [label="Intermediate (Any) -1" color=black];
        OP580 -> OP582 [label="Const (int) -0" color=black];
        OP574 -> OP584 [label="Intermediate (Any) -1" color=black];
        OP582 -> OP584 [label="Intermediate (Any) -0" color=black];
        OP566 -> OP586 [label="Intermediate (Any) -1" color=black];
        OP584 -> OP586 [label="Intermediate (Any) -0" color=black];
        OP586 -> OP590 [label="Intermediate (Any) -0" color=black];
        OP592 -> OP594 [label="Const (bool) -0" color=black];
        OP596 -> OP598 [label="Local (NESPPU) -0" color=black];
        OP598 -> OP600 [label="Intermediate (NESPPU) -0" color=black];
        OP600 -> OP604 [label="Intermediate (int) -1" color=black];
        OP602 -> OP604 [label="Const (int) -0" color=black];
        OP598 -> OP606 [label="Intermediate (NESPPU) -1" color=black];
        OP604 -> OP606 [label="Intermediate (big int) -0" color=black];
        OP606 -> OP608 [label="Intermediate (big int) -1" color=black];
        OP606 -> OP608 [label="Intermediate (NESPPU) -0" color=black];
        OP610 -> OP612 [label="Local (NESPPU) -0" color=black];
        OP612 -> OP614 [label="Intermediate (NESPPU) -0" color=black];
        OP614 -> OP618 [label="Intermediate (int) -1" color=black];
        OP616 -> OP618 [label="Const (int) -0" color=black];
        OP612 -> OP620 [label="Intermediate (NESPPU) -1" color=black];
        OP618 -> OP620 [label="Intermediate (big int) -0" color=black];
        OP620 -> OP622 [label="Intermediate (big int) -1" color=black];
        OP620 -> OP622 [label="Intermediate (NESPPU) -0" color=black];
        OP624 -> OP626 [label="Local (NESPPU) -0" color=black];
        OP626 -> OP628 [label="Intermediate (NESPPU) -0" color=black];
        OP628 -> OP632 [label="Intermediate (int) -1" color=black];
        OP630 -> OP632 [label="Const (int) -0" color=black];
        OP626 -> OP634 [label="Intermediate (NESPPU) -1" color=black];
        OP632 -> OP634 [label="Intermediate (big int) -0" color=black];
        OP634 -> OP636 [label="Intermediate (big int) -1" color=black];
        OP634 -> OP636 [label="Intermediate (NESPPU) -0" color=black];
        OP638 -> OP640 [label="Local (NESPPU) -0" color=black];
        OP640 -> OP644 [label="Intermediate (int) -1" color=black];
        OP642 -> OP644 [label="Const (int) -0" color=black];
        OP644 -> OP648 [label="Intermediate (bool) -0" color=black];
        OP650 -> OP652 [label="Local (NESPPU) -0" color=black];
        OP652 -> OP656 [label="Intermediate (int) -1" color=black];
        OP654 -> OP656 [label="Const (int) -0" color=black];
        OP656 -> OP660 [label="Intermediate (big int) -1" color=black];
        OP658 -> OP660 [label="Const (int) -0" color=black];
        OP660 -> OP664 [label="Intermediate (bool) -0" color=black];
        OP666 -> OP668 [label="Local (NESPPU) -0" color=black];
        OP668 -> OP670 [label="Intermediate (NESPPU) -0" color=black];
        OP670 -> OP674 [label="Intermediate (Any) -1" color=black];
        OP672 -> OP674 [label="Const (int) -0" color=black];
        OP668 -> OP676 [label="Intermediate (NESPPU) -1" color=black];
        OP674 -> OP676 [label="Intermediate (Any) -0" color=black];
        OP676 -> OP678 [label="Intermediate (Any) -1" color=black];
        OP676 -> OP678 [label="Intermediate (NESPPU) -0" color=black];
        OP680 -> OP682 [label="Local (NESPPU) -0" color=black];
        OP684 -> OP686 [label="Local (NESPPU) -0" color=black];
        OP682 -> OP688 [label="Intermediate (int) -1" color=black];
        OP686 -> OP688 [label="Intermediate (int) -0" color=black];
        OP688 -> OP692 [label="Intermediate (bool) -0" color=black];
        OP694 -> OP696 [label="Local (NESPPU) -0" color=black];
        OP696 -> OP698 [label="Intermediate (NESPPU) -0" color=black];
        OP698 -> OP702 [label="Intermediate (Any) -1" color=black];
        OP700 -> OP702 [label="Const (int) -0" color=black];
        OP696 -> OP704 [label="Intermediate (NESPPU) -1" color=black];
        OP702 -> OP704 [label="Intermediate (Any) -0" color=black];
        OP704 -> OP706 [label="Intermediate (Any) -1" color=black];
        OP704 -> OP706 [label="Intermediate (NESPPU) -0" color=black];
        OP708 -> OP712 [label="Const (int) -1" color=black];
        OP710 -> OP712 [label="Local (NESPPU) -0" color=black];
        OP714 -> OP718 [label="Const (int) -1" color=black];
        OP716 -> OP718 [label="Local (NESPPU) -0" color=black];
        OP720 -> OP722 [label="Local (NESPPU) -0" color=black];
        OP722 -> OP726 [label="Intermediate (Any) -1" color=black];
        OP724 -> OP726 [label="Const (int) -0" color=black];
        OP726 -> OP730 [label="Intermediate (Any) -0" color=black];
        OP732 -> OP734 [label="Local (NESPPU) -0" color=black];
        OP734 -> OP738 [label="Intermediate (Any) -1" color=black];
        OP736 -> OP738 [label="Const (int) -0" color=black];
        OP738 -> OP742 [label="Intermediate (Any) -1" color=black];
        OP740 -> OP742 [label="Const (int) -0" color=black];
        OP742 -> OP746 [label="Intermediate (Any) -0" color=black];
        OP748 -> OP750 [label="Local (NESPPU) -0" color=black];
        OP750 -> OP752 [label="Intermediate (NESPPU) -0" color=black];
        OP752 -> OP756 [label="Intermediate (Any) -1" color=black];
        OP754 -> OP756 [label="Const (int) -0" color=black];
        OP750 -> OP758 [label="Intermediate (NESPPU) -1" color=black];
        OP756 -> OP758 [label="Intermediate (Any) -0" color=black];
        OP758 -> OP760 [label="Intermediate (Any) -1" color=black];
        OP758 -> OP760 [label="Intermediate (NESPPU) -0" color=black];
        OP762 -> OP766 [label="Local (bool) -0" color=black];
        OP768 -> OP770 [label="Local (NESPPU) -0" color=black];
        OP770 -> OP772 [label="Intermediate (NESPPU) -1" color=black];
        OP770 -> OP772 [label="Method (method) -0" color=black];
        OP772 -> OP774 [label="Intermediate (Any) -0" color=black];
}

digraph _overlay_sprites { 
        node [shape=box];
        FRAME [label=FRAME];
        OP0 [label="0 LOAD_FAST ('bkg_pixel')" color="black"];
        OP2 [label="2 STORE_FAST ('c_out')" color="black"];
        OP4 [label="4 LOAD_FAST ('self')" color="black"];
        OP6 [label="6 LOAD_ATTR (ppu_mask)" color="black"];
        OP8 [label="8 LOAD_FAST ('self')" color="black"];
        OP10 [label="10 LOAD_ATTR (RENDER_SPRITES_MASK)" color="black"];
        OP12 [label="12 BINARY_AND (0)" color="black"];
        OP14 [label="14 LOAD_CONST (0)" color="red"];
        OP16 [label="16 COMPARE_OP (2)" color="black"];
        OP18 [label="18 POP_JUMP_IF_TRUE (24)" color="red"];
        OP18 -> OP20 [label="Jump (conditional)" color=orange];
        OP18 -> OP48 [label="Jump (conditional)" color=orange];
        OP20 [label="20 LOAD_FAST ('self')" color="black"];
        OP22 [label="22 LOAD_ATTR (pixel)" color="black"];
        OP24 [label="24 LOAD_CONST (1)" color="red"];
        OP26 [label="26 BINARY_SUBTRACT (0)" color="black"];
        OP28 [label="28 LOAD_CONST (8)" color="red"];
        OP30 [label="30 COMPARE_OP (0)" color="black"];
        OP32 [label="32 POP_JUMP_IF_FALSE (26)" color="red"];
        OP32 -> OP34 [label="Jump (conditional)" color=orange];
        OP32 -> OP52 [label="Jump (conditional)" color=orange];
        OP34 [label="34 LOAD_GLOBAL (bit_low)" color="black"];
        OP36 [label="36 LOAD_FAST ('self')" color="black"];
        OP38 [label="38 LOAD_ATTR (ppu_mask)" color="black"];
        OP40 [label="40 LOAD_FAST ('self')" color="black"];
        OP42 [label="42 LOAD_ATTR (RENDER_LEFT8_SPRITES_BIT)" color="black"];
        OP44 [label="44 CALL_FUNCTION (2)" color="black"];
        OP46 [label="46 POP_JUMP_IF_FALSE (26)" color="black"];
        OP46 -> OP48 [label="Jump (conditional)" color=orange];
        OP46 -> OP52 [label="Jump (conditional)" color=orange];
        OP48 [label="48 LOAD_FAST ('c_out')" color="black"];
        OP50 [label="50 RETURN_VALUE (0)" color="black"];
        OP52 [label="52 LOAD_CONST ((None, None))" color="black"];
        OP54 [label="54 UNPACK_SEQUENCE (2)" color="black"];
        OP56 [label="56 STORE_FAST ('sprite_c_out')" color="black"];
        OP58 [label="58 STORE_FAST ('top_sprite')" color="black"];
        OP60 [label="60 LOAD_CONST (False)" color="blue"];
        OP62 [label="62 STORE_FAST ('s0_visible')" color="blue"];
        OP64 [label="64 LOAD_GLOBAL (reversed)" color="black"];
        OP66 [label="66 LOAD_GLOBAL (range)" color="black"];
        OP68 [label="68 LOAD_GLOBAL (len)" color="black"];
        OP70 [label="70 LOAD_FAST ('self')" color="black"];
        OP72 [label="72 LOAD_ATTR (_active_sprites)" color="black"];
        OP74 [label="74 CALL_FUNCTION (1)" color="black"];
        OP76 [label="76 CALL_FUNCTION (1)" color="black"];
        OP78 [label="78 CALL_FUNCTION (1)" color="black"];
        OP80 [label="80 GET_ITER (0)" color="black"];
        OP82 [label="82 FOR_ITER (57)" color="black"];
        OP82 -> OP84 [label="Jump (conditional)" color=orange];
        OP82 -> OP198 [label="Jump (conditional)" color=orange];
        OP84 [label="84 STORE_FAST ('i')" color="black"];
        OP86 [label="86 LOAD_FAST ('self')" color="black"];
        OP88 [label="88 LOAD_ATTR (_active_sprites)" color="black"];
        OP90 [label="90 LOAD_FAST ('i')" color="black"];
        OP92 [label="92 BINARY_SUBSCR (0)" color="black"];
        OP94 [label="94 STORE_FAST ('sprite_addr')" color="black"];
        OP96 [label="96 LOAD_FAST ('self')" color="black"];
        OP98 [label="98 LOAD_ATTR (oam)" color="black"];
        OP100 [label="100 LOAD_FAST ('sprite_addr')" color="black"];
        OP102 [label="102 LOAD_CONST (3)" color="red"];
        OP104 [label="104 BINARY_ADD (0)" color="black"];
        OP106 [label="106 BINARY_SUBSCR (0)" color="black"];
        OP108 [label="108 STORE_FAST ('sprite_x')" color="black"];
        OP110 [label="110 LOAD_FAST ('sprite_x')" color="black"];
        OP112 [label="112 LOAD_FAST ('self')" color="black"];
        OP114 [label="114 LOAD_ATTR (pixel)" color="black"];
        OP116 [label="116 LOAD_CONST (1)" color="red"];
        OP118 [label="118 BINARY_SUBTRACT (0)" color="black"];
        OP120 [label="120 DUP_TOP (0)" color="black"];
        OP122 [label="122 ROT_THREE (0)" color="black"];
        OP124 [label="124 COMPARE_OP (1)" color="black"];
        OP126 [label="126 POP_JUMP_IF_FALSE (70)" color="black"];
        OP126 -> OP128 [label="Jump (conditional)" color=orange];
        OP126 -> OP140 [label="Jump (conditional)" color=orange];
        OP128 [label="128 LOAD_FAST ('sprite_x')" color="black"];
        OP130 [label="130 LOAD_CONST (8)" color="red"];
        OP132 [label="132 BINARY_ADD (0)" color="black"];
        OP134 [label="134 COMPARE_OP (0)" color="black"];
        OP136 [label="136 POP_JUMP_IF_FALSE (98)" color="black"];
        OP136 -> OP138 [label="Jump (conditional)" color=orange];
        OP136 -> OP196 [label="Jump (conditional)" color=orange];
        OP138 [label="138 JUMP_FORWARD (2)" color="black"];
        OP138 -> OP144 [label="Jump" color=yellow];
        OP140 [label="140 POP_TOP (0)" color="black"];
        OP142 [label="142 JUMP_ABSOLUTE (41)" color="black"];
        OP142 -> OP82 [label="Jump" color=yellow];
        OP144 [label="144 LOAD_FAST ('self')" color="black"];
        OP146 [label="146 LOAD_ATTR (pixel)" color="black"];
        OP148 [label="148 LOAD_CONST (1)" color="red"];
        OP150 [label="150 BINARY_SUBTRACT (0)" color="black"];
        OP152 [label="152 LOAD_FAST ('sprite_x')" color="black"];
        OP154 [label="154 BINARY_SUBTRACT (0)" color="black"];
        OP156 [label="156 STORE_FAST ('pix')" color="black"];
        OP158 [label="158 LOAD_FAST ('self')" color="black"];
        OP160 [label="160 LOAD_ATTR (_sprite_pattern)" color="black"];
        OP162 [label="162 LOAD_FAST ('i')" color="black"];
        OP164 [label="164 BINARY_SUBSCR (0)" color="black"];
        OP166 [label="166 LOAD_FAST ('pix')" color="black"];
        OP168 [label="168 BINARY_SUBSCR (0)" color="black"];
        OP170 [label="170 STORE_FAST ('c')" color="black"];
        OP172 [label="172 LOAD_FAST ('c')" color="black"];
        OP174 [label="174 POP_JUMP_IF_FALSE (98)" color="black"];
        OP174 -> OP176 [label="Jump (conditional)" color=orange];
        OP174 -> OP196 [label="Jump (conditional)" color=orange];
        OP176 [label="176 LOAD_FAST ('i')" color="black"];
        OP178 [label="178 STORE_FAST ('top_sprite')" color="black"];
        OP180 [label="180 LOAD_FAST ('c')" color="black"];
        OP182 [label="182 STORE_FAST ('sprite_c_out')" color="black"];
        OP184 [label="184 LOAD_FAST ('sprite_addr')" color="black"];
        OP186 [label="186 LOAD_CONST (0)" color="red"];
        OP188 [label="188 COMPARE_OP (2)" color="black"];
        OP190 [label="190 POP_JUMP_IF_FALSE (98)" color="black"];
        OP190 -> OP192 [label="Jump (conditional)" color=orange];
        OP190 -> OP196 [label="Jump (conditional)" color=orange];
        OP192 [label="192 LOAD_CONST (True)" color="blue"];
        OP194 [label="194 STORE_FAST ('s0_visible')" color="blue"];
        OP196 [label="196 JUMP_ABSOLUTE (41)" color="black"];
        OP196 -> OP82 [label="Jump" color=yellow];
        OP198 [label="198 LOAD_FAST ('s0_visible')" color="blue"];
        OP200 [label="200 POP_JUMP_IF_FALSE (109)" color="blue"];
        OP200 -> OP202 [label="Jump (conditional)" color=orange];
        OP200 -> OP218 [label="Jump (conditional)" color=orange];
        OP202 [label="202 LOAD_FAST ('bkg_pixel')" color="black"];
        OP204 [label="204 LOAD_FAST ('self')" color="black"];
        OP206 [label="206 LOAD_ATTR (transparent_color)" color="black"];
        OP208 [label="208 COMPARE_OP (3)" color="black"];
        OP210 [label="210 POP_JUMP_IF_FALSE (109)" color="black"];
        OP210 -> OP212 [label="Jump (conditional)" color=orange];
        OP210 -> OP218 [label="Jump (conditional)" color=orange];
        OP212 [label="212 LOAD_CONST (True)" color="red"];
        OP214 [label="214 LOAD_FAST ('self')" color="black"];
        OP216 [label="216 STORE_ATTR (sprite_zero_hit)" color="black"];
        OP218 [label="218 LOAD_FAST ('sprite_c_out')" color="black"];
        OP220 [label="220 POP_JUMP_IF_FALSE (123)" color="black"];
        OP220 -> OP222 [label="Jump (conditional)" color=orange];
        OP220 -> OP246 [label="Jump (conditional)" color=orange];
        OP222 [label="222 LOAD_FAST ('self')" color="black"];
        OP224 [label="224 LOAD_ATTR (_sprite_bkg_priority)" color="black"];
        OP226 [label="226 LOAD_FAST ('top_sprite')" color="black"];
        OP228 [label="228 BINARY_SUBSCR (0)" color="black"];
        OP230 [label="230 POP_JUMP_IF_FALSE (121)" color="black"];
        OP230 -> OP232 [label="Jump (conditional)" color=orange];
        OP230 -> OP242 [label="Jump (conditional)" color=orange];
        OP232 [label="232 LOAD_FAST ('bkg_pixel')" color="black"];
        OP234 [label="234 LOAD_FAST ('self')" color="black"];
        OP236 [label="236 LOAD_ATTR (transparent_color)" color="black"];
        OP238 [label="238 COMPARE_OP (2)" color="black"];
        OP240 [label="240 POP_JUMP_IF_FALSE (123)" color="black"];
        OP240 -> OP242 [label="Jump (conditional)" color=orange];
        OP240 -> OP246 [label="Jump (conditional)" color=orange];
        OP242 [label="242 LOAD_FAST ('sprite_c_out')" color="black"];
        OP244 [label="244 STORE_FAST ('c_out')" color="black"];
        OP246 [label="246 LOAD_FAST ('c_out')" color="black"];
        OP248 [label="248 LOAD_FAST ('self')" color="black"];
        OP250 [label="250 LOAD_ATTR (transparent_color)" color="black"];
        OP252 [label="252 COMPARE_OP (3)" color="black"];
        OP254 [label="254 POP_JUMP_IF_FALSE (130)" color="red"];
        OP254 -> OP256 [label="Jump (conditional)" color=orange];
        OP254 -> OP260 [label="Jump (conditional)" color=orange];
        OP256 [label="256 LOAD_FAST ('c_out')" color="black"];
        OP258 [label="258 RETURN_VALUE (0)" color="black"];
        OP260 [label="260 LOAD_FAST ('self')" color="black"];
        OP262 [label="262 LOAD_METHOD (decode_palette)" color="black"];
        OP264 [label="264 LOAD_CONST (0)" color="red"];
        OP266 [label="266 CALL_METHOD (1)" color="black"];
        OP268 [label="268 LOAD_CONST (0)" color="red"];
        OP270 [label="270 BINARY_SUBSCR (0)" color="black"];
        OP272 [label="272 RETURN_VALUE (0)" color="black"];
        OP0 -> OP2 [label="Local (tuple) -0" color=black];
        OP4 -> OP6 [label="Local (NESPPU) -0" color=black];
        OP8 -> OP10 [label="Local (NESPPU) -0" color=black];
        OP6 -> OP12 [label="Intermediate (int) -1" color=black];
        OP10 -> OP12 [label="Intermediate (int) -0" color=black];
        OP12 -> OP16 [label="Intermediate (big int) -1" color=black];
        OP14 -> OP16 [label="Const (int) -0" color=black];
        OP16 -> OP18 [label="Intermediate (bool) -0" color=black];
        OP20 -> OP22 [label="Local (NESPPU) -0" color=black];
        OP22 -> OP26 [label="Intermediate (int) -1" color=black];
        OP24 -> OP26 [label="Const (int) -0" color=black];
        OP26 -> OP30 [label="Intermediate (big int) -1" color=black];
        OP28 -> OP30 [label="Const (int) -0" color=black];
        OP30 -> OP32 [label="Intermediate (bool) -0" color=black];
        OP36 -> OP38 [label="Local (NESPPU) -0" color=black];
        OP40 -> OP42 [label="Local (NESPPU) -0" color=black];
        OP34 -> OP44 [label="Global (function) -2" color=black];
        OP38 -> OP44 [label="Intermediate (int) -1" color=black];
        OP42 -> OP44 [label="Intermediate (int) -0" color=black];
        OP44 -> OP46 [label="Local (Any) -0" color=black];
        OP48 -> OP50 [label="Local (tuple) -0" color=black];
        OP52 -> OP54 [label="Const (tuple) -0" color=black];
        OP54 -> OP56 [label="Intermediate (NoneType) -0" color=black];
        OP54 -> OP58 [label="Intermediate (NoneType) -0" color=black];
        OP60 -> OP62 [label="Const (bool) UN0" color=purple];
        OP70 -> OP72 [label="Local (NESPPU) -0" color=black];
        OP68 -> OP74 [label="Builtin (function) -1" color=black];
        OP72 -> OP74 [label="Intermediate (list) -0" color=black];
        OP66 -> OP76 [label="Builtin (type) -1" color=black];
        OP74 -> OP76 [label="Local (int) -0" color=black];
        OP64 -> OP78 [label="Builtin (type) -1" color=black];
        OP76 -> OP78 [label="Local (range) -0" color=black];
        OP78 -> OP80 [label="Local (reversed) -0" color=black];
        OP80 -> OP82 [label="Intermediate (Any) -0" color=black];
        OP82 -> OP84 [label="Intermediate (Any) -0" color=black];
        OP86 -> OP88 [label="Local (NESPPU) -0" color=black];
        OP88 -> OP92 [label="Intermediate (Any) -1" color=black];
        OP90 -> OP92 [label="Local (Any) -0" color=black];
        OP92 -> OP94 [label="Intermediate (Any) -0" color=black];
        OP96 -> OP98 [label="Local (NESPPU) -0" color=black];
        OP100 -> OP104 [label="Local (Any) -1" color=black];
        OP102 -> OP104 [label="Const (int) -0" color=black];
        OP98 -> OP106 [label="Intermediate (Any) -1" color=black];
        OP104 -> OP106 [label="Intermediate (Any) -0" color=black];
        OP106 -> OP108 [label="Intermediate (Any) -0" color=black];
        OP112 -> OP114 [label="Local (NESPPU) -0" color=black];
        OP114 -> OP118 [label="Intermediate (Any) -1" color=black];
        OP116 -> OP118 [label="Const (int) -0" color=black];
        OP118 -> OP120 [label="Intermediate (Any) -0" color=black];
        OP110 -> OP122 [label="Local (Any) -2" color=black];
        OP120 -> OP122 [label="Intermediate (Any) -1" color=black];
        OP120 -> OP122 [label="Intermediate (Any) -0" color=black];
        OP122 -> OP124 [label="Intermediate (Any) -1" color=black];
        OP122 -> OP124 [label="Intermediate (Any) -0" color=black];
        OP124 -> OP126 [label="Intermediate (Any) -0" color=black];
        OP128 -> OP132 [label="Local (Any) -1" color=black];
        OP130 -> OP132 [label="Const (int) -0" color=black];
        OP122 -> OP134 [label="Intermediate (Any) -1" color=black];
        OP132 -> OP134 [label="Intermediate (Any) -0" color=black];
        OP134 -> OP136 [label="Intermediate (Any) -0" color=black];
        OP122 -> OP140 [label="Intermediate (Any) -0" color=black];
        OP144 -> OP146 [label="Local (NESPPU) -0" color=black];
        OP146 -> OP150 [label="Intermediate (Any) -1" color=black];
        OP148 -> OP150 [label="Const (int) -0" color=black];
        OP150 -> OP154 [label="Intermediate (Any) -1" color=black];
        OP152 -> OP154 [label="Local (Any) -0" color=black];
        OP154 -> OP156 [label="Intermediate (Any) -0" color=black];
        OP158 -> OP160 [label="Local (NESPPU) -0" color=black];
        OP160 -> OP164 [label="Intermediate (Any) -1" color=black];
        OP162 -> OP164 [label="Local (Any) -0" color=black];
        OP164 -> OP168 [label="Intermediate (Any) -1" color=black];
        OP166 -> OP168 [label="Local (Any) -0" color=black];
        OP168 -> OP170 [label="Intermediate (Any) -0" color=black];
        OP172 -> OP174 [label="Local (Any) -0" color=black];
        OP176 -> OP178 [label="Local (Any) -0" color=black];
        OP180 -> OP182 [label="Local (Any) -0" color=black];
        OP184 -> OP188 [label="Local (Any) -1" color=black];
        OP186 -> OP188 [label="Const (int) -0" color=black];
        OP188 -> OP190 [label="Intermediate (Any) -0" color=black];
        OP192 -> OP194 [label="Const (bool) UN0" color=purple];
        OP198 -> OP200 [label="Local (bool) UN0" color=purple];
        OP204 -> OP206 [label="Local (NESPPU) -0" color=black];
        OP202 -> OP208 [label="Local (tuple) -1" color=black];
        OP206 -> OP208 [label="Intermediate (Any) -0" color=black];
        OP208 -> OP210 [label="Intermediate (Any) -0" color=black];
        OP212 -> OP216 [label="Const (bool) -1" color=black];
        OP214 -> OP216 [label="Local (NESPPU) -0" color=black];
        OP218 -> OP220 [label="Local (Any) -0" color=black];
        OP222 -> OP224 [label="Local (NESPPU) -0" color=black];
        OP224 -> OP228 [label="Intermediate (Any) -1" color=black];
        OP226 -> OP228 [label="Local (Any) -0" color=black];
        OP228 -> OP230 [label="Intermediate (Any) -0" color=black];
        OP234 -> OP236 [label="Local (NESPPU) -0" color=black];
        OP232 -> OP238 [label="Local (tuple) -1" color=black];
        OP236 -> OP238 [label="Intermediate (Any) -0" color=black];
        OP238 -> OP240 [label="Intermediate (Any) -0" color=black];
        OP242 -> OP244 [label="Local (Any) -0" color=black];
        OP248 -> OP250 [label="Local (NESPPU) -0" color=black];
        OP246 -> OP252 [label="Local (tuple) -1" color=black];
        OP250 -> OP252 [label="Intermediate (tuple) -0" color=black];
        OP252 -> OP254 [label="Intermediate (bool) -0" color=black];
        OP256 -> OP258 [label="Local (Any) -0" color=black];
        OP260 -> OP262 [label="Local (NESPPU) -0" color=black];
        OP262 -> OP266 [label="Intermediate (NESPPU) -2" color=black];
        OP262 -> OP266 [label="Method (method) -1" color=black];
        OP264 -> OP266 [label="Const (int) -0" color=black];
        OP266 -> OP270 [label="Intermediate (list) -1" color=black];
        OP268 -> OP270 [label="Const (int) -0" color=black];
        OP270 -> OP272 [label="Intermediate (Any) -0" color=black];
}

digraph _get_bkg_pixel { 
        node [shape=box];
        FRAME [label=FRAME];
        OP0 [label="0 LOAD_FAST ('self')" color="black"];
        OP2 [label="2 LOAD_ATTR (ppu_mask)" color="black"];
        OP4 [label="4 LOAD_FAST ('self')" color="black"];
        OP6 [label="6 LOAD_ATTR (RENDER_BACKGROUND_MASK)" color="black"];
        OP8 [label="8 BINARY_AND (0)" color="black"];
        OP10 [label="10 LOAD_CONST (0)" color="red"];
        OP12 [label="12 COMPARE_OP (2)" color="black"];
        OP14 [label="14 POP_JUMP_IF_TRUE (22)" color="red"];
        OP14 -> OP16 [label="Jump (conditional)" color=orange];
        OP14 -> OP44 [label="Jump (conditional)" color=orange];
        OP16 [label="16 LOAD_FAST ('self')" color="black"];
        OP18 [label="18 LOAD_ATTR (pixel)" color="black"];
        OP20 [label="20 LOAD_CONST (1)" color="red"];
        OP22 [label="22 BINARY_SUBTRACT (0)" color="black"];
        OP24 [label="24 LOAD_CONST (8)" color="red"];
        OP26 [label="26 COMPARE_OP (0)" color="black"];
        OP28 [label="28 POP_JUMP_IF_FALSE (25)" color="red"];
        OP28 -> OP30 [label="Jump (conditional)" color=orange];
        OP28 -> OP50 [label="Jump (conditional)" color=orange];
        OP30 [label="30 LOAD_GLOBAL (bit_low)" color="black"];
        OP32 [label="32 LOAD_FAST ('self')" color="black"];
        OP34 [label="34 LOAD_ATTR (ppu_mask)" color="black"];
        OP36 [label="36 LOAD_FAST ('self')" color="black"];
        OP38 [label="38 LOAD_ATTR (RENDER_LEFT8_BKG_BIT)" color="black"];
        OP40 [label="40 CALL_FUNCTION (2)" color="black"];
        OP42 [label="42 POP_JUMP_IF_FALSE (25)" color="black"];
        OP42 -> OP44 [label="Jump (conditional)" color=orange];
        OP42 -> OP50 [label="Jump (conditional)" color=orange];
        OP44 [label="44 LOAD_FAST ('self')" color="black"];
        OP46 [label="46 LOAD_ATTR (transparent_color)" color="black"];
        OP48 [label="48 RETURN_VALUE (0)" color="black"];
        OP50 [label="50 LOAD_FAST ('self')" color="black"];
        OP52 [label="52 LOAD_ATTR (ppu_scroll)" color="black"];
        OP54 [label="54 LOAD_FAST ('self')" color="black"];
        OP56 [label="56 LOAD_ATTR (PPU_SCROLL_X)" color="black"];
        OP58 [label="58 BINARY_SUBSCR (0)" color="black"];
        OP60 [label="60 LOAD_CONST (7)" color="red"];
        OP62 [label="62 BINARY_AND (0)" color="black"];
        OP64 [label="64 STORE_FAST ('fine_x')" color="black"];
        OP66 [label="66 LOAD_FAST ('self')" color="black"];
        OP68 [label="68 LOAD_ATTR (pixel)" color="black"];
        OP70 [label="70 LOAD_CONST (1)" color="red"];
        OP72 [label="72 BINARY_SUBTRACT (0)" color="black"];
        OP74 [label="74 LOAD_CONST (8)" color="red"];
        OP76 [label="76 BINARY_MODULO (0)" color="black"];
        OP78 [label="78 LOAD_FAST ('fine_x')" color="black"];
        OP80 [label="80 BINARY_ADD (0)" color="black"];
        OP82 [label="82 STORE_FAST ('px')" color="black"];
        OP84 [label="84 LOAD_CONST (1)" color="red"];
        OP86 [label="86 LOAD_CONST (15)" color="red"];
        OP88 [label="88 LOAD_FAST ('px')" color="black"];
        OP90 [label="90 BINARY_SUBTRACT (0)" color="black"];
        OP92 [label="92 BINARY_LSHIFT (0)" color="black"];
        OP94 [label="94 STORE_FAST ('mask')" color="black"];
        OP96 [label="96 LOAD_FAST ('self')" color="black"];
        OP98 [label="98 LOAD_ATTR (_pattern_lo)" color="black"];
        OP100 [label="100 LOAD_FAST ('mask')" color="black"];
        OP102 [label="102 BINARY_AND (0)" color="black"];
        OP104 [label="104 LOAD_CONST (0)" color="red"];
        OP106 [label="106 COMPARE_OP (4)" color="black"];
        OP108 [label="108 LOAD_FAST ('self')" color="black"];
        OP110 [label="110 LOAD_ATTR (_pattern_hi)" color="black"];
        OP112 [label="112 LOAD_FAST ('mask')" color="black"];
        OP114 [label="114 BINARY_AND (0)" color="black"];
        OP116 [label="116 LOAD_CONST (0)" color="red"];
        OP118 [label="118 COMPARE_OP (4)" color="black"];
        OP120 [label="120 LOAD_CONST (2)" color="red"];
        OP122 [label="122 BINARY_MULTIPLY (0)" color="black"];
        OP124 [label="124 BINARY_ADD (0)" color="black"];
        OP126 [label="126 STORE_FAST ('v')" color="blue"];
        OP128 [label="128 LOAD_FAST ('v')" color="blue"];
        OP130 [label="130 LOAD_CONST (0)" color="blue"];
        OP132 [label="132 COMPARE_OP (4)" color="blue"];
        OP134 [label="134 POP_JUMP_IF_FALSE (79)" color="blue"];
        OP134 -> OP136 [label="Jump (conditional)" color=orange];
        OP134 -> OP158 [label="Jump (conditional)" color=orange];
        OP136 [label="136 LOAD_FAST ('self')" color="black"];
        OP138 [label="138 LOAD_ATTR (_palette)" color="black"];
        OP140 [label="140 LOAD_GLOBAL (int)" color="black"];
        OP142 [label="142 LOAD_FAST ('px')" color="black"];
        OP144 [label="144 LOAD_CONST (8)" color="red"];
        OP146 [label="146 BINARY_TRUE_DIVIDE (0)" color="black"];
        OP148 [label="148 CALL_FUNCTION (1)" color="black"];
        OP150 [label="150 BINARY_SUBSCR (0)" color="black"];
        OP152 [label="152 LOAD_FAST ('v')" color="blue"];
        OP154 [label="154 BINARY_SUBSCR (0)" color="black"];
        OP156 [label="156 RETURN_VALUE (0)" color="black"];
        OP158 [label="158 LOAD_FAST ('self')" color="black"];
        OP160 [label="160 LOAD_ATTR (transparent_color)" color="black"];
        OP162 [label="162 RETURN_VALUE (0)" color="black"];
        OP0 -> OP2 [label="Local (NESPPU) -0" color=black];
        OP4 -> OP6 [label="Local (NESPPU) -0" color=black];
        OP2 -> OP8 [label="Intermediate (int) -1" color=black];
        OP6 -> OP8 [label="Intermediate (int) -0" color=black];
        OP8 -> OP12 [label="Intermediate (big int) -1" color=black];
        OP10 -> OP12 [label="Const (int) -0" color=black];
        OP12 -> OP14 [label="Intermediate (bool) -0" color=black];
        OP16 -> OP18 [label="Local (NESPPU) -0" color=black];
        OP18 -> OP22 [label="Intermediate (int) -1" color=black];
        OP20 -> OP22 [label="Const (int) -0" color=black];
        OP22 -> OP26 [label="Intermediate (big int) -1" color=black];
        OP24 -> OP26 [label="Const (int) -0" color=black];
        OP26 -> OP28 [label="Intermediate (bool) -0" color=black];
        OP32 -> OP34 [label="Local (NESPPU) -0" color=black];
        OP36 -> OP38 [label="Local (NESPPU) -0" color=black];
        OP30 -> OP40 [label="Global (function) -2" color=black];
        OP34 -> OP40 [label="Intermediate (int) -1" color=black];
        OP38 -> OP40 [label="Intermediate (int) -0" color=black];
        OP40 -> OP42 [label="Local (Any) -0" color=black];
        OP44 -> OP46 [label="Local (NESPPU) -0" color=black];
        OP46 -> OP48 [label="Intermediate (Any) -0" color=black];
        OP50 -> OP52 [label="Local (NESPPU) -0" color=black];
        OP54 -> OP56 [label="Local (NESPPU) -0" color=black];
        OP52 -> OP58 [label="Intermediate (bytearray) -1" color=black];
        OP56 -> OP58 [label="Intermediate (int) -0" color=black];
        OP58 -> OP62 [label="Intermediate (int) -1" color=black];
        OP60 -> OP62 [label="Const (int) -0" color=black];
        OP62 -> OP64 [label="Intermediate (big int) -0" color=black];
        OP66 -> OP68 [label="Local (NESPPU) -0" color=black];
        OP68 -> OP72 [label="Intermediate (int) -1" color=black];
        OP70 -> OP72 [label="Const (int) -0" color=black];
        OP72 -> OP76 [label="Intermediate (big int) -1" color=black];
        OP74 -> OP76 [label="Const (int) -0" color=black];
        OP76 -> OP80 [label="Intermediate (big int) -1" color=black];
        OP78 -> OP80 [label="Local (big int) -0" color=black];
        OP80 -> OP82 [label="Intermediate (big int) -0" color=black];
        OP86 -> OP90 [label="Const (int) -1" color=black];
        OP88 -> OP90 [label="Local (big int) -0" color=black];
        OP84 -> OP92 [label="Const (int) -1" color=black];
        OP90 -> OP92 [label="Intermediate (big int) -0" color=black];
        OP92 -> OP94 [label="Intermediate (big int) -0" color=black];
        OP96 -> OP98 [label="Local (NESPPU) -0" color=black];
        OP98 -> OP102 [label="Intermediate (int) -1" color=black];
        OP100 -> OP102 [label="Local (big int) -0" color=black];
        OP102 -> OP106 [label="Intermediate (big int) -1" color=black];
        OP104 -> OP106 [label="Const (int) -0" color=black];
        OP108 -> OP110 [label="Local (NESPPU) -0" color=black];
        OP110 -> OP114 [label="Intermediate (int) -1" color=black];
        OP112 -> OP114 [label="Local (big int) -0" color=black];
        OP114 -> OP118 [label="Intermediate (big int) -1" color=black];
        OP116 -> OP118 [label="Const (int) -0" color=black];
        OP118 -> OP122 [label="Intermediate (bool) -1" color=black];
        OP120 -> OP122 [label="Const (int) -0" color=black];
        OP106 -> OP124 [label="Intermediate (bool) -1" color=black];
        OP122 -> OP124 [label="Intermediate (int) -0" color=black];
        OP124 -> OP126 [label="Intermediate (int) U0" color=red];
        OP128 -> OP132 [label="Local (int) UN1" color=purple];
        OP130 -> OP132 [label="Const (int) UN0" color=purple];
        OP132 -> OP134 [label="Intermediate (bool) UN0" color=purple];
        OP136 -> OP138 [label="Local (NESPPU) -0" color=black];
        OP142 -> OP146 [label="Local (big int) -1" color=black];
        OP144 -> OP146 [label="Const (int) -0" color=black];
        OP140 -> OP148 [label="Builtin (type) -1" color=black];
        OP146 -> OP148 [label="Intermediate (float) -0" color=black];
        OP138 -> OP150 [label="Intermediate (Any) -1" color=black];
        OP148 -> OP150 [label="Local (big int) -0" color=black];
        OP150 -> OP154 [label="Intermediate (Any) -1" color=black];
        OP152 -> OP154 [label="Local (int) B0" color=green];
        OP154 -> OP156 [label="Intermediate (Any) -0" color=black];
        OP158 -> OP160 [label="Local (NESPPU) -0" color=black];
        OP160 -> OP162 [label="Intermediate (Any) -0" color=black];
}